json_compare/__init__.py
json_compare/is_close.py
json_compare/json_compare.py
json_compare/test/__init__.py
json_compare/test/jsondiffstack.py
json_compare/test/test_json_compare.py
json_compare-0.2.11.dist-info/DESCRIPTION.rst
json_compare-0.2.11.dist-info/METADATA
json_compare-0.2.11.dist-info/RECORD
json_compare-0.2.11.dist-info/WHEEL
json_compare-0.2.11.dist-info/metadata.json
json_compare-0.2.11.dist-info/top_level.txt
