Metadata-Version: 2.0
Name: json-compare
Version: 0.2.11
Summary: Json comparison tool
Home-page: https://github.com/darthghandi/jsoncompare
Author: Chris Saxey
Author-email: chrissaxey@gmail.com
License: UNKNOWN
Keywords: json comparison compare order
Platform: UNKNOWN
Requires-Dist: future
Requires-Dist: python-rapidjson
